diffusion_cbor.cpython-38-x86_64-linux-gnu.so
diffusion_cbor.libs/libstdc++-a9383cce.so.6.0.28
diffusion_cbor.libs/libgcc_s-a04fdf82.so.1
diffusion_cbor-6.7.5.dist-info/WHEEL
diffusion_cbor-6.7.5.dist-info/RECORD
diffusion_cbor-6.7.5.dist-info/METADATA
diffusion_cbor-6.7.5.dist-info/top_level.txt
diffusion_cbor-6.7.5.dist-info/LICENSE
