Metadata-Version: 2.1
Name: diffusion-cbor
Version: 6.7.5
Summary: Python SDK for Diffusion - CBOR serialisation.
Home-page: 
License: Proprietary
Keywords: diffusion,cloud,websockets,data,cbor
Platform: UNKNOWN
Classifier: License :: Other/Proprietary License
Classifier: Environment :: Other Environment
Classifier: Development Status :: 4 - Beta
License-File: LICENSE
